shoppingcart.py
mindpowered_shoppingcart/ShoppingCart.py
mindpowered_shoppingcart/__init__.py
mindpowered_shoppingcart-0.0.14.dist-info/LICENSE.txt
mindpowered_shoppingcart-0.0.14.dist-info/METADATA
mindpowered_shoppingcart-0.0.14.dist-info/WHEEL
mindpowered_shoppingcart-0.0.14.dist-info/top_level.txt
mindpowered_shoppingcart-0.0.14.dist-info/RECORD
