Metadata-Version: 2.1
Name: mindpowered-shoppingcart
Version: 0.0.14
Summary: Shopping Cart for Online Shopping
Home-page: https://mindpowered.dev/
Author: Mind Powered Corporation
Author-email: support@mindpowered.dev
License: MIT
Platform: UNKNOWN
Classifier: Programming Language :: Python :: 3
Classifier: Operating System :: OS Independent
Classifier: License :: OSI Approved :: MIT License
Requires-Dist: mindpowered-maglev
